{
    "argon2cost": {
        "time": 3,
        "memory": 81920,
        "threads": 2,
        "keyLen": 32,
        "saltLen": 32
    },
    "cloudflare": {
        "enabled": false
    },
    "cookie": {
        "prefix": "allocamelus_"
    },
    "db": {
        "Net": "unix",
        "server": "/var/run/mysqld/mysqld.sock",
        "name": "databaseName",
        "username": "user",
        "password": "password (Don\"t use this one)"
    },
    "dev": false,
    "googleClient": {
        "enabled": false,
        "id": "",
        "key": "Path to client secret json"
    },
    "hcaptcha": {
        "enabled": false,
        "secret": "",
        "easy": "",
        "moderate": "",
        "hard": "",
        "all": ""
    },
    "logs": {
        "level": 2,
        "path": "app.log"
    },
    "mail": {
        "enabled": true,
        "insecure": false,
        "server": "mail.example.com",
        "sender": "bot@example.com",
        "username": "user",
        "password": "password"
    },
    "path": {
        "media": "media/",
        "tmpDir": "/tmp/allocamelus_tmp_dir",
        "public": {
            "verifyEmail": "/account/verify-email",
            "resetPassword": "/account/reset-password",
            "media": "/media/"
        }
    },
    "redis": {
        "host": "/var/run/redis/redis-server.sock",
        "user": "",
        "password": ""
    },
    "session": {
        "maxLife": 86400,
        "expiration": 900
    },
    "site": {
        "description": "Explore Example",
        "domain": "example.com",
        "name": "Example",
        "port": 8080,
        "prefork": false
    },
    "ssl": {
        "enabled": false,
        "cert": "Path to ssl Cert",
        "key": "Path to ssl Key",
        "port": 8443
    }
}